StockClockUtils/StockDataUtils.py
StockClockUtils/__init__.py
stockclockutils-0.0.4.dist-info/LICENSE
stockclockutils-0.0.4.dist-info/METADATA
stockclockutils-0.0.4.dist-info/WHEEL
stockclockutils-0.0.4.dist-info/top_level.txt
stockclockutils-0.0.4.dist-info/RECORD
